odoo/addons/ssi_mrp_landed_cost/README.rst
odoo/addons/ssi_mrp_landed_cost/__init__.py
odoo/addons/ssi_mrp_landed_cost/__manifest__.py
odoo/addons/ssi_mrp_landed_cost/models/__init__.py
odoo/addons/ssi_mrp_landed_cost/models/stock_landed_cost.py
odoo/addons/ssi_mrp_landed_cost/static/description/icon.png
odoo14_addon_ssi_mrp_landed_cost-14.0.2.0.0.dist-info/METADATA
odoo14_addon_ssi_mrp_landed_cost-14.0.2.0.0.dist-info/WHEEL
odoo14_addon_ssi_mrp_landed_cost-14.0.2.0.0.dist-info/top_level.txt
odoo14_addon_ssi_mrp_landed_cost-14.0.2.0.0.dist-info/RECORD
